speak_command/__init__.py
speak_command/speak_command/__init__.py
speak_command/speak_command/speak_command.py
speak_command/waka_command/PocketSphinx.py
speak_command/waka_command/__init__.py
speak_command/waka_command/command_api.py
speak_command/waka_command/pyaudio_demo.py
speak_command/waka_command/waka_command.py
speak_command/waka_command/command_tasks/WeatherAPITest.py
speak_command/waka_command/command_tasks/__init__.py
speak_command/waka_command/command_tasks/baidu_spider.py
speak_command/waka_command/command_tasks/cnki.py
speak_command/waka_command/command_tasks/selenium_csdn.py
speak_command/waka_command/command_tasks/time_know.py
speak_command-0.1.0.dist-info/METADATA
speak_command-0.1.0.dist-info/WHEEL
speak_command-0.1.0.dist-info/top_level.txt
speak_command-0.1.0.dist-info/RECORD
